{
  "index": "NIFTY",
  "date": "2026-04-13",
  "final_score": -81.10592600706728,
  "regime": "SHOCK",
  "shock_score": 6.270048161873963,
  "participants": [
    {
      "name": "DII",
      "bias": -1.4628361232687543,
      "label": "Bearish"
    },
    {
      "name": "FII",
      "bias": -5.710727867816889,
      "label": "Strong Bearish"
    },
    {
      "name": "PRO",
      "bias": 0.3513423932506985,
      "label": "Neutral"
    },
    {
      "name": "RETAIL",
      "bias": 2.112218947118696,
      "label": "Strong Bullish"
    }
  ],
  "bias_Label": "Bearish",
  "strength": "Strong",
  "explanation": "Shock regime detected (shock=6.3). Top driver: FII (-5.71, Strong Bearish). Composite bias is bearish.",
  "pcr": null,
  "vix": null,
  "pcr_volume": null,
  "banknifty_pcr": null,
  "banknifty_pcr_volume": null,
  "participant_activity": [
    {
      "participant": "FII",
      "instrument": "Futures",
      "net_oi_change": -2127,
      "vs_yesterday_pct": -1.03
    },
    {
      "participant": "FII",
      "instrument": "Calls",
      "net_oi_change": -27604,
      "vs_yesterday_pct": -15.46
    },
    {
      "participant": "FII",
      "instrument": "Puts",
      "net_oi_change": -7960,
      "vs_yesterday_pct": -2.39
    },
    {
      "participant": "DII",
      "instrument": "Futures",
      "net_oi_change": 483,
      "vs_yesterday_pct": 0.77
    },
    {
      "participant": "DII",
      "instrument": "Calls",
      "net_oi_change": 70,
      "vs_yesterday_pct": 7.51
    },
    {
      "participant": "DII",
      "instrument": "Puts",
      "net_oi_change": 4750,
      "vs_yesterday_pct": 8.94
    },
    {
      "participant": "PRO",
      "instrument": "Futures",
      "net_oi_change": 3526,
      "vs_yesterday_pct": 3874.73
    },
    {
      "participant": "PRO",
      "instrument": "Calls",
      "net_oi_change": -46764,
      "vs_yesterday_pct": -91.87
    },
    {
      "participant": "PRO",
      "instrument": "Puts",
      "net_oi_change": 7487,
      "vs_yesterday_pct": 10.28
    }
  ]
}