[
  {
    "date": "2026-06-08",
    "final_score": -100,
    "regime": "SHOCK"
  },
  {
    "date": "2026-06-09",
    "final_score": -100,
    "regime": "SHOCK"
  },
  {
    "date": "2026-06-10",
    "final_score": -99.98548086461909,
    "regime": "SHOCK"
  },
  {
    "date": "2026-06-11",
    "final_score": -99.98606045849692,
    "regime": "SHOCK"
  },
  {
    "date": "2026-06-12",
    "final_score": -99.45066493777442,
    "regime": "SHOCK"
  },
  {
    "date": "2026-06-15",
    "final_score": -99.84126957824475,
    "regime": "SHOCK"
  },
  {
    "date": "2026-06-16",
    "final_score": -99.8566414958858,
    "regime": "SHOCK"
  },
  {
    "date": "2026-06-17",
    "final_score": -99.99625349913975,
    "regime": "SHOCK"
  },
  {
    "date": "2026-06-18",
    "final_score": -99.90612562439097,
    "regime": "SHOCK"
  },
  {
    "date": "2026-06-19",
    "final_score": -87.71873005213499,
    "regime": "SHOCK"
  },
  {
    "date": "2026-06-22",
    "final_score": -79.08396789948374,
    "regime": "SHOCK"
  },
  {
    "date": "2026-06-23",
    "final_score": -89.55747692627324,
    "regime": "SHOCK"
  },
  {
    "date": "2026-06-24",
    "final_score": -85.76975851810134,
    "regime": "SHOCK"
  },
  {
    "date": "2026-06-25",
    "final_score": -95.48992376166251,
    "regime": "SHOCK"
  },
  {
    "date": "2026-06-29",
    "final_score": -96.28598994483133,
    "regime": "SHOCK"
  },
  {
    "date": "2026-06-30",
    "final_score": -90.35271191624547,
    "regime": "SHOCK"
  },
  {
    "date": "2026-07-01",
    "final_score": -86.34227014042123,
    "regime": "SHOCK"
  },
  {
    "date": "2026-07-02",
    "final_score": -83.39104900153839,
    "regime": "SHOCK"
  },
  {
    "date": "2026-07-03",
    "final_score": -94.97264216926929,
    "regime": "SHOCK"
  },
  {
    "date": "2026-07-06",
    "final_score": -72.40848786491102,
    "regime": "SHOCK"
  }
]